{"name":"ApiEventStream","description":null,"summary":null,"attributes":[{"name":"ReplayId","type":"string"},{"name":"CreatedDate","type":"datetime"},{"name":"EventUuid","type":"string"},{"name":"EventIdentifier","type":"string"},{"name":"UserId","type":"reference"},{"name":"Username","type":"string"},{"name":"EventDate","type":"datetime"},{"name":"RelatedEventIdentifier","type":"string"},{"name":"LoginHistoryId","type":"reference"},{"name":"RowsProcessed","type":"double"},{"name":"RowsReturned","type":"double"},{"name":"Operation","type":"picklist"},{"name":"QueriedEntities","type":"string"},{"name":"PolicyId","type":"reference"},{"name":"PolicyOutcome","type":"picklist"},{"name":"EvaluationTime","type":"double"},{"name":"SessionKey","type":"string"},{"name":"LoginKey","type":"string"},{"name":"SessionLevel","type":"picklist"},{"name":"SourceIp","type":"string"},{"name":"AdditionalInfo","type":"string"},{"name":"ApiType","type":"string"},{"name":"ApiVersion","type":"double"},{"name":"Application","type":"string"},{"name":"Client","type":"string"},{"name":"ConnectedAppId","type":"string"},{"name":"ElapsedTime","type":"int"},{"name":"Platform","type":"string"},{"name":"Query","type":"textarea"},{"name":"Records","type":"json"},{"name":"UserAgent","type":"string"}]}