{"name":"ManagedContentChannel","description":null,"summary":null,"attributes":[{"name":"Id","type":"id"},{"name":"IsDeleted","type":"boolean"},{"name":"Name","type":"string"},{"name":"CreatedDate","type":"datetime"},{"name":"CreatedById","type":"reference"},{"name":"LastModifiedDate","type":"datetime"},{"name":"LastModifiedById","type":"reference"},{"name":"SystemModstamp","type":"datetime"},{"name":"Type","type":"picklist"},{"name":"OptionsIsSearchable","type":"boolean"},{"name":"OptionsIsCacheControlPublic","type":"boolean"},{"name":"OptionsIsDomainLocked","type":"boolean"},{"name":"Domain","type":"picklist"},{"name":"DomainHostName","type":"string"},{"name":"CacheControlMaxAge","type":"long"}]}