{"name":"Group","description":"Represents a group of users.","summary":"In Salesforce, the `Group` object is used to define and manage groups of users within the organization. Here's a summary of the `Group` object:\n\n### Overview\n- **Purpose**: The `Group` object is designed to organize users into specific groups for various purposes such as sharing records, assigning permissions, and managing access.\n- **Usage**: Groups can be used in conjunction with roles, queues, and other sharing mechanisms to control data access and facilitate collaboration within the organization.\n\n### Key Fields\n- **Id**: Unique identifier for the group.\n- **Name**: The name of the group.\n- **Type**: The type of group (e.g., Regular, Queue, Role, RoleAndSubordinates).\n- **RelatedId**: The ID of the related record (e.g., a queue or role).\n- **OwnerId**: The ID of the user who owns the group.\n- **CreatedById**: The ID of the user who created the group.\n- **CreatedDate**: The date and time when the group was created.\n- **LastModifiedById**: The ID of the user who last modified the group.\n- **LastModifiedDate**: The date and time when the group was last modified.\n\n### Types of Groups\n- **Regular Group**: A standard group of users.\n- **Queue**: A special type of group used to manage the distribution of records like cases, leads, and custom objects.\n- **Role**: A group that represents a hierarchical role within the organization.\n- **RoleAndSubordinates**: A group that includes a role and all its subordinate roles.\n\n### Use Cases\n- **Record Sharing**: Groups can be used to share records with multiple users at once.\n- **Queue Management**: Queues can be used to manage the assignment of records to a group of users.\n- **Permission Sets**: Groups can be assigned permission sets to manage access to various features and data.\n- **Collaboration**: Groups can facilitate collaboration by allowing users to share information and work together on records.\n\n### Relationships\n- **Users**: Groups can contain multiple users.\n- **Roles**: Groups can be associated with roles to manage hierarchical access.\n- **Queues**: Groups can be used as queues to manage the distribution of","attributes":[{"name":"Id","type":"id"},{"name":"Name","type":"string"},{"name":"DeveloperName","type":"string"},{"name":"RelatedId","type":"reference"},{"name":"Type","type":"picklist"},{"name":"Email","type":"email"},{"name":"OwnerId","type":"reference"},{"name":"DoesSendEmailToMembers","type":"boolean"},{"name":"DoesIncludeBosses","type":"boolean"},{"name":"CreatedDate","type":"datetime"},{"name":"CreatedById","type":"reference"},{"name":"LastModifiedDate","type":"datetime"},{"name":"LastModifiedById","type":"reference"},{"name":"SystemModstamp","type":"datetime"}],"label":"Group","application":"salesforce","attributesString":"[{\"name\":\"Id\",\"type\":\"id\"},{\"name\":\"Name\",\"type\":\"string\"},{\"name\":\"DeveloperName\",\"type\":\"string\"},{\"name\":\"RelatedId\",\"type\":\"reference\"},{\"name\":\"Type\",\"type\":\"picklist\"},{\"name\":\"Email\",\"type\":\"email\"},{\"name\":\"OwnerId\",\"type\":\"reference\"},{\"name\":\"DoesSendEmailToMembers\",\"type\":\"boolean\"},{\"name\":\"DoesIncludeBosses\",\"type\":\"boolean\"},{\"name\":\"CreatedDate\",\"type\":\"datetime\"},{\"name\":\"CreatedById\",\"type\":\"reference\"},{\"name\":\"LastModifiedDate\",\"type\":\"datetime\"},{\"name\":\"LastModifiedById\",\"type\":\"reference\"},{\"name\":\"SystemModstamp\",\"type\":\"datetime\"}]"}