{"name":"Note","description":"Represents a note that a user can attach to a parent object record.","summary":"In Salesforce, the `Note` object is used to store and manage notes related to various records within the application. Here's a summary of its key features and functionalities:\n\n1. **Purpose**: The `Note` object allows users to create, edit, and delete notes that can be associated with other records such as Accounts, Contacts, Opportunities, Cases, and custom objects.\n\n2. **Fields**: Some of the standard fields in the `Note` object include:\n   - `Id`: Unique identifier of the note.\n   - `ParentId`: ID of the record to which the note is related.\n   - `Title`: Title or subject of the note.\n   - `Body`: Content or text of the note.\n   - `IsPrivate`: Indicates whether the note is private.\n   - `CreatedById`: ID of the user who created the note.\n   - `CreatedDate`: Date and time when the note was created.\n   - `LastModifiedById`: ID of the user who last modified the note.\n   - `LastModifiedDate`: Date and time when the note was last modified.\n\n3. **Relationships**: The `Note` object has a polymorphic relationship with other objects in Salesforce, allowing it to be linked to various types of records.\n\n4. **Access**: Access to notes can be controlled through permissions and sharing settings. Users can also mark notes as private to restrict visibility.\n\n5. **User Interface**: Notes can be viewed and managed in the related lists of associated records, as well as in the Notes tab (if enabled).\n\n6. **API Access**: The `Note` object can be accessed and manipulated using Salesforce APIs, such as SOAP API, REST API, and Bulk API.\n\n7. **Enhanced Notes**: Salesforce also offers Enhanced Notes, which provide additional features like rich text formatting, inline images, and larger note size. Enhanced Notes are stored in the `ContentNote` and `ContentDocumentLink` objects.\n\nThe `Note` object is essential for tracking interactions, storing additional information, and facilitating collaboration among users in Salesforce.","attributes":[{"name":"Id","type":"id"},{"name":"IsDeleted","type":"boolean"},{"name":"ParentId","type":"reference"},{"name":"Title","type":"string"},{"name":"IsPrivate","type":"boolean"},{"name":"Body","type":"textarea"},{"name":"OwnerId","type":"reference"},{"name":"CreatedDate","type":"datetime"},{"name":"CreatedById","type":"reference"},{"name":"LastModifiedDate","type":"datetime"},{"name":"LastModifiedById","type":"reference"},{"name":"SystemModstamp","type":"datetime"}],"label":"Note","application":"salesforce","attributesString":"[{\"name\":\"Id\",\"type\":\"id\"},{\"name\":\"IsDeleted\",\"type\":\"boolean\"},{\"name\":\"ParentId\",\"type\":\"reference\"},{\"name\":\"Title\",\"type\":\"string\"},{\"name\":\"IsPrivate\",\"type\":\"boolean\"},{\"name\":\"Body\",\"type\":\"textarea\"},{\"name\":\"OwnerId\",\"type\":\"reference\"},{\"name\":\"CreatedDate\",\"type\":\"datetime\"},{\"name\":\"CreatedById\",\"type\":\"reference\"},{\"name\":\"LastModifiedDate\",\"type\":\"datetime\"},{\"name\":\"LastModifiedById\",\"type\":\"reference\"},{\"name\":\"SystemModstamp\",\"type\":\"datetime\"}]"}