{"name":"imp_notification","description":"Manages email notifications sent to users based on certain events or conditions.","summary":"Sure, here's a summary of the `imp_notification` object in the context of the ServiceNow application:\n\n### imp_notification Object Summary\n\n**Object Name:** imp_notification\n\n**Application:** ServiceNow\n\n**Purpose:**\nThe `imp_notification` object is used to manage and track notifications related to the implementation of services or changes within the ServiceNow platform. It helps in communicating important updates, changes, or alerts to relevant stakeholders.\n\n**Key Attributes:**\n1. **Notification ID:** A unique identifier for each notification.\n2. **Title:** A brief title or subject of the notification.\n3. **Description:** Detailed information about the notification.\n4. **Type:** The type of notification (e.g., informational, warning, critical).\n5. **Status:** The current status of the notification (e.g., pending, sent, failed).\n6. **Recipients:** The users or groups who are intended to receive the notification.\n7. **Date/Time:** The timestamp when the notification was created or sent.\n8. **Priority:** The urgency or importance level of the notification.\n9. **Source:** The origin or initiator of the notification (e.g., system, user).\n\n**Common Use Cases:**\n1. **Service Announcements:** Informing users about upcoming maintenance, service outages, or new features.\n2. **Change Management:** Notifying stakeholders about changes in processes, policies, or system configurations.\n3. **Incident Alerts:** Sending alerts about critical incidents or issues that require immediate attention.\n4. **User Communications:** General communications to users about updates, reminders, or important information.\n\n**Integration:**\nThe `imp_notification` object can be integrated with other ServiceNow modules such as Incident Management, Change Management, and Problem Management to ensure timely and relevant notifications are sent to the appropriate users.\n\n**Customization:**\nAdministrators can customize the notification templates, delivery methods (e.g., email, SMS), and trigger conditions to fit the specific needs of their organization.\n\n**Reporting:**\nReports can be generated to track the effectiveness of notifications, including metrics like delivery success rates, user engagement, and response times.\n\nBy effectively utilizing the `imp_notification` object, organizations can","attributes":[{"name":"assignment_group","type":"string"},{"name":"sys_import_state_comment","type":"string"},{"name":"expires_on","type":"string"},{"name":"template_import_log","type":"reference"},{"name":"source","type":"string"},{"name":"sys_updated_on","type":"glide_date_time"},{"name":"type","type":"string"},{"name":"uuid","type":"string"},{"name":"sys_class_name","type":"sys_class_name"},{"name":"sys_target_sys_id","type":"document_id"},{"name":"duration","type":"string"},{"name":"sys_id","type":"GUID"},{"name":"sys_updated_by","type":"string"},{"name":"sys_created_on","type":"glide_date_time"},{"name":"sys_import_set","type":"reference"},{"name":"sys_transform_map","type":"reference"},{"name":"state","type":"string"},{"name":"sys_created_by","type":"string"},{"name":"timestamp","type":"string"},{"name":"sys_import_row","type":"integer"},{"name":"severity","type":"string"},{"name":"sys_row_error","type":"reference"},{"name":"comments","type":"string"},{"name":"sys_target_table","type":"table_name"},{"name":"sys_mod_count","type":"integer"},{"name":"import_set_run","type":"reference"},{"name":"message","type":"string"},{"name":"sys_tags","type":"related_tags"},{"name":"sys_import_state","type":"string"},{"name":"category","type":"string"},{"name":"corrective_message","type":"string"}],"label":"Notification","application":"servicenow","attributesString":"[{\"name\":\"assignment_group\",\"type\":\"string\"},{\"name\":\"sys_import_state_comment\",\"type\":\"string\"},{\"name\":\"expires_on\",\"type\":\"string\"},{\"name\":\"template_import_log\",\"type\":\"reference\"},{\"name\":\"source\",\"type\":\"string\"},{\"name\":\"sys_updated_on\",\"type\":\"glide_date_time\"},{\"name\":\"type\",\"type\":\"string\"},{\"name\":\"uuid\",\"type\":\"string\"},{\"name\":\"sys_class_name\",\"type\":\"sys_class_name\"},{\"name\":\"sys_target_sys_id\",\"type\":\"document_id\"},{\"name\":\"duration\",\"type\":\"string\"},{\"name\":\"sys_id\",\"type\":\"GUID\"},{\"name\":\"sys_updated_by\",\"type\":\"string\"},{\"name\":\"sys_created_on\",\"type\":\"glide_date_time\"},{\"name\":\"sys_import_set\",\"type\":\"reference\"},{\"name\":\"sys_transform_map\",\"type\":\"reference\"},{\"name\":\"state\",\"type\":\"string\"},{\"name\":\"sys_created_by\",\"type\":\"string\"},{\"name\":\"timestamp\",\"type\":\"string\"},{\"name\":\"sys_import_row\",\"type\":\"integer\"},{\"name\":\"severity\",\"type\":\"string\"},{\"name\":\"sys_row_error\",\"type\":\"reference\"},{\"name\":\"comments\",\"type\":\"string\"},{\"name\":\"sys_target_table\",\"type\":\"table_name\"},{\"name\":\"sys_mod_count\",\"type\":\"integer\"},{\"name\":\"import_set_run\",\"type\":\"reference\"},{\"name\":\"message\",\"type\":\"string\"},{\"name\":\"sys_tags\",\"type\":\"related_tags\"},{\"name\":\"sys_import_state\",\"type\":\"string\"},{\"name\":\"category\",\"type\":\"string\"},{\"name\":\"corrective_message\",\"type\":\"string\"}]"}