{"name":"sys_script_include","description":"Server-side reusable scripts that can be invoked from other server-side scripts.","summary":null,"attributes":[{"name":"client_callable","type":"boolean"},{"name":"access","type":"string"},{"name":"sys_mod_count","type":"integer"},{"name":"description","type":"string"},{"name":"active","type":"boolean"},{"name":"sys_updated_on","type":"glide_date_time"},{"name":"sys_tags","type":"related_tags"},{"name":"script","type":"script_plain"},{"name":"sys_class_name","type":"sys_class_name"},{"name":"sys_id","type":"GUID"},{"name":"sys_package","type":"reference"},{"name":"sys_update_name","type":"string"},{"name":"sys_updated_by","type":"string"},{"name":"api_name","type":"string"},{"name":"sys_created_on","type":"glide_date_time"},{"name":"caller_access","type":"string"},{"name":"name","type":"string"},{"name":"sys_name","type":"string"},{"name":"sys_scope","type":"reference"},{"name":"sys_created_by","type":"string"},{"name":"sys_policy","type":"string"}],"label":"Script Include","application":"servicenow","attributesString":"[{\"name\":\"client_callable\",\"type\":\"boolean\"},{\"name\":\"access\",\"type\":\"string\"},{\"name\":\"sys_mod_count\",\"type\":\"integer\"},{\"name\":\"description\",\"type\":\"string\"},{\"name\":\"active\",\"type\":\"boolean\"},{\"name\":\"sys_updated_on\",\"type\":\"glide_date_time\"},{\"name\":\"sys_tags\",\"type\":\"related_tags\"},{\"name\":\"script\",\"type\":\"script_plain\"},{\"name\":\"sys_class_name\",\"type\":\"sys_class_name\"},{\"name\":\"sys_id\",\"type\":\"GUID\"},{\"name\":\"sys_package\",\"type\":\"reference\"},{\"name\":\"sys_update_name\",\"type\":\"string\"},{\"name\":\"sys_updated_by\",\"type\":\"string\"},{\"name\":\"api_name\",\"type\":\"string\"},{\"name\":\"sys_created_on\",\"type\":\"glide_date_time\"},{\"name\":\"caller_access\",\"type\":\"string\"},{\"name\":\"name\",\"type\":\"string\"},{\"name\":\"sys_name\",\"type\":\"string\"},{\"name\":\"sys_scope\",\"type\":\"reference\"},{\"name\":\"sys_created_by\",\"type\":\"string\"},{\"name\":\"sys_policy\",\"type\":\"string\"}]"}